project1/src/baseline/relu_s20.v
module relu_s20 (
    input  wire signed [19:0] x_s20,
    output wire [7:0] y_u8
);
    wire signed [19:0] x_clip_low;
    assign x_clip_low = (x_s20 < 0) ? 20'sd0 : x_s20;
    assign y_u8 = (x_clip_low > 20'sd255) ? 8'd255 : x_clip_low[7:0];
endmodule

project1/sim/tb_relu_s20.v
`timescale 1ns/1ps

module tb_relu_s20;
    reg signed [19:0] x_s20;
    wire [7:0] y_u8;

    integer iv;
    integer expected;

    relu_s20 dut (
        .x_s20(x_s20),
        .y_u8(y_u8)
    );

    task automatic check_value;
        input integer val;
        input integer exp;
        begin
            x_s20 = val;
            #1;
            if (y_u8 !== exp[7:0]) begin
                $display("tb_relu_s20 FAIL x=%0d got=%0d exp=%0d", val, y_u8, exp);
                $finish;
            end
        end
    endtask

    initial begin
        check_value(-524288, 0);
        check_value(-300, 0);
        check_value(-1, 0);
        check_value(0, 0);
        check_value(1, 1);
        check_value(127, 127);
        check_value(255, 255);
        check_value(256, 255);
        check_value(1024, 255);
        check_value(524287, 255);

        for (iv = -300; iv <= 600; iv = iv + 1) begin
            if (iv < 0) begin
                expected = 0;
            end else if (iv > 255) begin
                expected = 255;
            end else begin
                expected = iv;
            end
            check_value(iv, expected);
        end

        $display("tb_relu_s20 PASS");
        $finish;
    end
endmodule

project1/build/xsim/waves/tb_relu_s20.vcd
$date
   Sun Apr 26 18:11:39 2026
$end

$version
  2025.1.0
$end

$timescale
  1ps
$end

$scope module tb_relu_s20 $end
$var reg 20 ! x_s20 [19:0] $end
$var wire 8 " y_u8 [7:0] $end
$var integer 32 # iv [31:0] $end
$var integer 32 $ expected [31:0] $end
$scope module dut $end
$var wire 20 % x_s20 [19:0] $end
$var wire 8 " y_u8 [7:0] $end
$var wire 20 & x_clip_low [19:0] $end
$upscope $end
$upscope $end
$enddefinitions $end

#0
$dumpvars
b10000000000000000000 !
b0 "
bx #
bx $
b10000000000000000000 %
b0 &
$end

#1000
b11111111111011010100 !
b11111111111011010100 %

#2000
b11111111111111111111 !
b11111111111111111111 %

#3000
b0 !
b0 %

#4000
b1 !
b1 "
b1 %
b1 &

#5000
b1111111 !
b1111111 "
b1111111 %
b1111111 &

#6000
b11111111 !
b11111111 "
b11111111 %
b11111111 &

#7000
b100000000 !
b100000000 %
b100000000 &

#8000
b10000000000 !
b10000000000 %
b10000000000 &

#9000
b1111111111111111111 !
b1111111111111111111 %
b1111111111111111111 &

#10000
b11111111111011010100 !
b0 "
b11111111111111111111111011010100 #
b0 $
b11111111111011010100 %
b0 &

#11000
b11111111111011010101 !
b11111111111111111111111011010101 #
b11111111111011010101 %

#12000
b11111111111011010110 !
b11111111111111111111111011010110 #
b11111111111011010110 %

#13000
b11111111111011010111 !
b11111111111111111111111011010111 #
b11111111111011010111 %

#14000
b11111111111011011000 !
b11111111111111111111111011011000 #
b11111111111011011000 %

#15000
b11111111111011011001 !
b11111111111111111111111011011001 #
b11111111111011011001 %

#16000
b11111111111011011010 !
b11111111111111111111111011011010 #
b11111111111011011010 %

#17000
b11111111111011011011 !
b11111111111111111111111011011011 #
b11111111111011011011 %

#18000
b11111111111011011100 !
b11111111111111111111111011011100 #
b11111111111011011100 %

#19000
b11111111111011011101 !
b11111111111111111111111011011101 #
b11111111111011011101 %

#20000
b11111111111011011110 !
b11111111111111111111111011011110 #
b11111111111011011110 %

#21000
b11111111111011011111 !
b11111111111111111111111011011111 #
b11111111111011011111 %

#22000
b11111111111011100000 !
b11111111111111111111111011100000 #
b11111111111011100000 %

#23000
b11111111111011100001 !
b11111111111111111111111011100001 #
b11111111111011100001 %

#24000
b11111111111011100010 !
b11111111111111111111111011100010 #
b11111111111011100010 %

#25000
b11111111111011100011 !
b11111111111111111111111011100011 #
b11111111111011100011 %

#26000
b11111111111011100100 !
b11111111111111111111111011100100 #
b11111111111011100100 %

#27000
b11111111111011100101 !
b11111111111111111111111011100101 #
b11111111111011100101 %

#28000
b11111111111011100110 !
b11111111111111111111111011100110 #
b11111111111011100110 %

#29000
b11111111111011100111 !
b11111111111111111111111011100111 #
b11111111111011100111 %

#30000
b11111111111011101000 !
b11111111111111111111111011101000 #
b11111111111011101000 %

#31000
b11111111111011101001 !
b11111111111111111111111011101001 #
b11111111111011101001 %

#32000
b11111111111011101010 !
b11111111111111111111111011101010 #
b11111111111011101010 %

#33000
b11111111111011101011 !
b11111111111111111111111011101011 #
b11111111111011101011 %

#34000
b11111111111011101100 !
b11111111111111111111111011101100 #
b11111111111011101100 %

#35000
b11111111111011101101 !
b11111111111111111111111011101101 #
b11111111111011101101 %

#36000
b11111111111011101110 !
b11111111111111111111111011101110 #
b11111111111011101110 %

#37000
b11111111111011101111 !
b11111111111111111111111011101111 #
b11111111111011101111 %

#38000
b11111111111011110000 !
b11111111111111111111111011110000 #
b11111111111011110000 %

#39000
b11111111111011110001 !
b11111111111111111111111011110001 #
b11111111111011110001 %

#40000
b11111111111011110010 !
b11111111111111111111111011110010 #
b11111111111011110010 %

#41000
b11111111111011110011 !
b11111111111111111111111011110011 #
b11111111111011110011 %

#42000
b11111111111011110100 !
b11111111111111111111111011110100 #
b11111111111011110100 %

#43000
b11111111111011110101 !
b11111111111111111111111011110101 #
b11111111111011110101 %

#44000
b11111111111011110110 !
b11111111111111111111111011110110 #
b11111111111011110110 %

#45000
b11111111111011110111 !
b11111111111111111111111011110111 #
b11111111111011110111 %

#46000
b11111111111011111000 !
b11111111111111111111111011111000 #
b11111111111011111000 %

#47000
b11111111111011111001 !
b11111111111111111111111011111001 #
b11111111111011111001 %

#48000
b11111111111011111010 !
b11111111111111111111111011111010 #
b11111111111011111010 %

#49000
b11111111111011111011 !
b11111111111111111111111011111011 #
b11111111111011111011 %

#50000
b11111111111011111100 !
b11111111111111111111111011111100 #
b11111111111011111100 %

#51000
b11111111111011111101 !
b11111111111111111111111011111101 #
b11111111111011111101 %

#52000
b11111111111011111110 !
b11111111111111111111111011111110 #
b11111111111011111110 %

#53000
b11111111111011111111 !
b11111111111111111111111011111111 #
b11111111111011111111 %

#54000
b11111111111100000000 !
b11111111111111111111111100000000 #
b11111111111100000000 %

#55000
b11111111111100000001 !
b11111111111111111111111100000001 #
b11111111111100000001 %

#56000
b11111111111100000010 !
b11111111111111111111111100000010 #
b11111111111100000010 %

#57000
b11111111111100000011 !
b11111111111111111111111100000011 #
b11111111111100000011 %

#58000
b11111111111100000100 !
b11111111111111111111111100000100 #
b11111111111100000100 %

#59000
b11111111111100000101 !
b11111111111111111111111100000101 #
b11111111111100000101 %

#60000
b11111111111100000110 !
b11111111111111111111111100000110 #
b11111111111100000110 %

#61000
b11111111111100000111 !
b11111111111111111111111100000111 #
b11111111111100000111 %

#62000
b11111111111100001000 !
b11111111111111111111111100001000 #
b11111111111100001000 %

#63000
b11111111111100001001 !
b11111111111111111111111100001001 #
b11111111111100001001 %

#64000
b11111111111100001010 !
b11111111111111111111111100001010 #
b11111111111100001010 %

#65000
b11111111111100001011 !
b11111111111111111111111100001011 #
b11111111111100001011 %

#66000
b11111111111100001100 !
b11111111111111111111111100001100 #
b11111111111100001100 %

#67000
b11111111111100001101 !
b11111111111111111111111100001101 #
b11111111111100001101 %

#68000
b11111111111100001110 !
b11111111111111111111111100001110 #
b11111111111100001110 %

#69000
b11111111111100001111 !
b11111111111111111111111100001111 #
b11111111111100001111 %

#70000
b11111111111100010000 !
b11111111111111111111111100010000 #
b11111111111100010000 %

#71000
b11111111111100010001 !
b11111111111111111111111100010001 #
b11111111111100010001 %

#72000
b11111111111100010010 !
b11111111111111111111111100010010 #
b11111111111100010010 %

#73000
b11111111111100010011 !
b11111111111111111111111100010011 #
b11111111111100010011 %

#74000
b11111111111100010100 !
b11111111111111111111111100010100 #
b11111111111100010100 %

#75000
b11111111111100010101 !
b11111111111111111111111100010101 #
b11111111111100010101 %

#76000
b11111111111100010110 !
b11111111111111111111111100010110 #
b11111111111100010110 %

#77000
b11111111111100010111 !
b11111111111111111111111100010111 #
b11111111111100010111 %

#78000
b11111111111100011000 !
b11111111111111111111111100011000 #
b11111111111100011000 %

#79000
b11111111111100011001 !
b11111111111111111111111100011001 #
b11111111111100011001 %

#80000
b11111111111100011010 !
b11111111111111111111111100011010 #
b11111111111100011010 %

#81000
b11111111111100011011 !
b11111111111111111111111100011011 #
b11111111111100011011 %

#82000
b11111111111100011100 !
b11111111111111111111111100011100 #
b11111111111100011100 %

#83000
b11111111111100011101 !
b11111111111111111111111100011101 #
b11111111111100011101 %

#84000
b11111111111100011110 !
b11111111111111111111111100011110 #
b11111111111100011110 %

#85000
b11111111111100011111 !
b11111111111111111111111100011111 #
b11111111111100011111 %

#86000
b11111111111100100000 !
b11111111111111111111111100100000 #
b11111111111100100000 %

#87000
b11111111111100100001 !
b11111111111111111111111100100001 #
b11111111111100100001 %

#88000
b11111111111100100010 !
b11111111111111111111111100100010 #
b11111111111100100010 %

#89000
b11111111111100100011 !
b11111111111111111111111100100011 #
b11111111111100100011 %

#90000
b11111111111100100100 !
b11111111111111111111111100100100 #
b11111111111100100100 %

#91000
b11111111111100100101 !
b11111111111111111111111100100101 #
b11111111111100100101 %

#92000
b11111111111100100110 !
b11111111111111111111111100100110 #
b11111111111100100110 %

#93000
b11111111111100100111 !
b11111111111111111111111100100111 #
b11111111111100100111 %

#94000
b11111111111100101000 !
b11111111111111111111111100101000 #
b11111111111100101000 %

#95000
b11111111111100101001 !
b11111111111111111111111100101001 #
b11111111111100101001 %

#96000
b11111111111100101010 !
b11111111111111111111111100101010 #
b11111111111100101010 %

#97000
b11111111111100101011 !
b11111111111111111111111100101011 #
b11111111111100101011 %

#98000
b11111111111100101100 !
b11111111111111111111111100101100 #
b11111111111100101100 %

#99000
b11111111111100101101 !
b11111111111111111111111100101101 #
b11111111111100101101 %

#100000
b11111111111100101110 !
b11111111111111111111111100101110 #
b11111111111100101110 %

#101000
b11111111111100101111 !
b11111111111111111111111100101111 #
b11111111111100101111 %

#102000
b11111111111100110000 !
b11111111111111111111111100110000 #
b11111111111100110000 %

#103000
b11111111111100110001 !
b11111111111111111111111100110001 #
b11111111111100110001 %

#104000
b11111111111100110010 !
b11111111111111111111111100110010 #
b11111111111100110010 %

#105000
b11111111111100110011 !
b11111111111111111111111100110011 #
b11111111111100110011 %

#106000
b11111111111100110100 !
b11111111111111111111111100110100 #
b11111111111100110100 %

#107000
b11111111111100110101 !
b11111111111111111111111100110101 #
b11111111111100110101 %

#108000
b11111111111100110110 !
b11111111111111111111111100110110 #
b11111111111100110110 %

#109000
b11111111111100110111 !
b11111111111111111111111100110111 #
b11111111111100110111 %

#110000
b11111111111100111000 !
b11111111111111111111111100111000 #
b11111111111100111000 %

#111000
b11111111111100111001 !
b11111111111111111111111100111001 #
b11111111111100111001 %

#112000
b11111111111100111010 !
b11111111111111111111111100111010 #
b11111111111100111010 %

#113000
b11111111111100111011 !
b11111111111111111111111100111011 #
b11111111111100111011 %

#114000
b11111111111100111100 !
b11111111111111111111111100111100 #
b11111111111100111100 %

#115000
b11111111111100111101 !
b11111111111111111111111100111101 #
b11111111111100111101 %

#116000
b11111111111100111110 !
b11111111111111111111111100111110 #
b11111111111100111110 %

#117000
b11111111111100111111 !
b11111111111111111111111100111111 #
b11111111111100111111 %

#118000
b11111111111101000000 !
b11111111111111111111111101000000 #
b11111111111101000000 %

#119000
b11111111111101000001 !
b11111111111111111111111101000001 #
b11111111111101000001 %

#120000
b11111111111101000010 !
b11111111111111111111111101000010 #
b11111111111101000010 %

#121000
b11111111111101000011 !
b11111111111111111111111101000011 #
b11111111111101000011 %

#122000
b11111111111101000100 !
b11111111111111111111111101000100 #
b11111111111101000100 %

#123000
b11111111111101000101 !
b11111111111111111111111101000101 #
b11111111111101000101 %

#124000
b11111111111101000110 !
b11111111111111111111111101000110 #
b11111111111101000110 %

#125000
b11111111111101000111 !
b11111111111111111111111101000111 #
b11111111111101000111 %

#126000
b11111111111101001000 !
b11111111111111111111111101001000 #
b11111111111101001000 %

#127000
b11111111111101001001 !
b11111111111111111111111101001001 #
b11111111111101001001 %

#128000
b11111111111101001010 !
b11111111111111111111111101001010 #
b11111111111101001010 %

#129000
b11111111111101001011 !
b11111111111111111111111101001011 #
b11111111111101001011 %

#130000
b11111111111101001100 !
b11111111111111111111111101001100 #
b11111111111101001100 %

#131000
b11111111111101001101 !
b11111111111111111111111101001101 #
b11111111111101001101 %

#132000
b11111111111101001110 !
b11111111111111111111111101001110 #
b11111111111101001110 %

#133000
b11111111111101001111 !
b11111111111111111111111101001111 #
b11111111111101001111 %

#134000
b11111111111101010000 !
b11111111111111111111111101010000 #
b11111111111101010000 %

#135000
b11111111111101010001 !
b11111111111111111111111101010001 #
b11111111111101010001 %

#136000
b11111111111101010010 !
b11111111111111111111111101010010 #
b11111111111101010010 %

#137000
b11111111111101010011 !
b11111111111111111111111101010011 #
b11111111111101010011 %

#138000
b11111111111101010100 !
b11111111111111111111111101010100 #
b11111111111101010100 %

#139000
b11111111111101010101 !
b11111111111111111111111101010101 #
b11111111111101010101 %

#140000
b11111111111101010110 !
b11111111111111111111111101010110 #
b11111111111101010110 %

#141000
b11111111111101010111 !
b11111111111111111111111101010111 #
b11111111111101010111 %

#142000
b11111111111101011000 !
b11111111111111111111111101011000 #
b11111111111101011000 %

#143000
b11111111111101011001 !
b11111111111111111111111101011001 #
b11111111111101011001 %

#144000
b11111111111101011010 !
b11111111111111111111111101011010 #
b11111111111101011010 %

#145000
b11111111111101011011 !
b11111111111111111111111101011011 #
b11111111111101011011 %

#146000
b11111111111101011100 !
b11111111111111111111111101011100 #
b11111111111101011100 %

#147000
b11111111111101011101 !
b11111111111111111111111101011101 #
b11111111111101011101 %

#148000
b11111111111101011110 !
b11111111111111111111111101011110 #
b11111111111101011110 %

#149000
b11111111111101011111 !
b11111111111111111111111101011111 #
b11111111111101011111 %

#150000
b11111111111101100000 !
b11111111111111111111111101100000 #
b11111111111101100000 %

#151000
b11111111111101100001 !
b11111111111111111111111101100001 #
b11111111111101100001 %

#152000
b11111111111101100010 !
b11111111111111111111111101100010 #
b11111111111101100010 %

#153000
b11111111111101100011 !
b11111111111111111111111101100011 #
b11111111111101100011 %

#154000
b11111111111101100100 !
b11111111111111111111111101100100 #
b11111111111101100100 %

#155000
b11111111111101100101 !
b11111111111111111111111101100101 #
b11111111111101100101 %

#156000
b11111111111101100110 !
b11111111111111111111111101100110 #
b11111111111101100110 %

#157000
b11111111111101100111 !
b11111111111111111111111101100111 #
b11111111111101100111 %

#158000
b11111111111101101000 !
b11111111111111111111111101101000 #
b11111111111101101000 %

#159000
b11111111111101101001 !
b11111111111111111111111101101001 #
b11111111111101101001 %

#160000
b11111111111101101010 !
b11111111111111111111111101101010 #
b11111111111101101010 %

#161000
b11111111111101101011 !
b11111111111111111111111101101011 #
b11111111111101101011 %

#162000
b11111111111101101100 !
b11111111111111111111111101101100 #
b11111111111101101100 %

#163000
b11111111111101101101 !
b11111111111111111111111101101101 #
b11111111111101101101 %

#164000
b11111111111101101110 !
b11111111111111111111111101101110 #
b11111111111101101110 %

#165000
b11111111111101101111 !
b11111111111111111111111101101111 #
b11111111111101101111 %

#166000
b11111111111101110000 !
b11111111111111111111111101110000 #
b11111111111101110000 %

#167000
b11111111111101110001 !
b11111111111111111111111101110001 #
b11111111111101110001 %

#168000
b11111111111101110010 !
b11111111111111111111111101110010 #
b11111111111101110010 %

#169000
b11111111111101110011 !
b11111111111111111111111101110011 #
b11111111111101110011 %

#170000
b11111111111101110100 !
b11111111111111111111111101110100 #
b11111111111101110100 %

#171000
b11111111111101110101 !
b11111111111111111111111101110101 #
b11111111111101110101 %

#172000
b11111111111101110110 !
b11111111111111111111111101110110 #
b11111111111101110110 %

#173000
b11111111111101110111 !
b11111111111111111111111101110111 #
b11111111111101110111 %

#174000
b11111111111101111000 !
b11111111111111111111111101111000 #
b11111111111101111000 %

#175000
b11111111111101111001 !
b11111111111111111111111101111001 #
b11111111111101111001 %

#176000
b11111111111101111010 !
b11111111111111111111111101111010 #
b11111111111101111010 %

#177000
b11111111111101111011 !
b11111111111111111111111101111011 #
b11111111111101111011 %

#178000
b11111111111101111100 !
b11111111111111111111111101111100 #
b11111111111101111100 %

#179000
b11111111111101111101 !
b11111111111111111111111101111101 #
b11111111111101111101 %

#180000
b11111111111101111110 !
b11111111111111111111111101111110 #
b11111111111101111110 %

#181000
b11111111111101111111 !
b11111111111111111111111101111111 #
b11111111111101111111 %

#182000
b11111111111110000000 !
b11111111111111111111111110000000 #
b11111111111110000000 %

#183000
b11111111111110000001 !
b11111111111111111111111110000001 #
b11111111111110000001 %

#184000
b11111111111110000010 !
b11111111111111111111111110000010 #
b11111111111110000010 %

#185000
b11111111111110000011 !
b11111111111111111111111110000011 #
b11111111111110000011 %

#186000
b11111111111110000100 !
b11111111111111111111111110000100 #
b11111111111110000100 %

#187000
b11111111111110000101 !
b11111111111111111111111110000101 #
b11111111111110000101 %

#188000
b11111111111110000110 !
b11111111111111111111111110000110 #
b11111111111110000110 %

#189000
b11111111111110000111 !
b11111111111111111111111110000111 #
b11111111111110000111 %

#190000
b11111111111110001000 !
b11111111111111111111111110001000 #
b11111111111110001000 %

#191000
b11111111111110001001 !
b11111111111111111111111110001001 #
b11111111111110001001 %

#192000
b11111111111110001010 !
b11111111111111111111111110001010 #
b11111111111110001010 %

#193000
b11111111111110001011 !
b11111111111111111111111110001011 #
b11111111111110001011 %

#194000
b11111111111110001100 !
b11111111111111111111111110001100 #
b11111111111110001100 %

#195000
b11111111111110001101 !
b11111111111111111111111110001101 #
b11111111111110001101 %

#196000
b11111111111110001110 !
b11111111111111111111111110001110 #
b11111111111110001110 %

#197000
b11111111111110001111 !
b11111111111111111111111110001111 #
b11111111111110001111 %

#198000
b11111111111110010000 !
b11111111111111111111111110010000 #
b11111111111110010000 %

#199000
b11111111111110010001 !
b11111111111111111111111110010001 #
b11111111111110010001 %

#200000
b11111111111110010010 !
b11111111111111111111111110010010 #
b11111111111110010010 %

#201000
b11111111111110010011 !
b11111111111111111111111110010011 #
b11111111111110010011 %

#202000
b11111111111110010100 !
b11111111111111111111111110010100 #
b11111111111110010100 %

#203000
b11111111111110010101 !
b11111111111111111111111110010101 #
b11111111111110010101 %

#204000
b11111111111110010110 !
b11111111111111111111111110010110 #
b11111111111110010110 %

#205000
b11111111111110010111 !
b11111111111111111111111110010111 #
b11111111111110010111 %

#206000
b11111111111110011000 !
b11111111111111111111111110011000 #
b11111111111110011000 %

#207000
b11111111111110011001 !
b11111111111111111111111110011001 #
b11111111111110011001 %

#208000
b11111111111110011010 !
b11111111111111111111111110011010 #
b11111111111110011010 %

#209000
b11111111111110011011 !
b11111111111111111111111110011011 #
b11111111111110011011 %

#210000
b11111111111110011100 !
b11111111111111111111111110011100 #
b11111111111110011100 %

#211000
b11111111111110011101 !
b11111111111111111111111110011101 #
b11111111111110011101 %

#212000
b11111111111110011110 !
b11111111111111111111111110011110 #
b11111111111110011110 %

#213000
b11111111111110011111 !
b11111111111111111111111110011111 #
b11111111111110011111 %

#214000
b11111111111110100000 !
b11111111111111111111111110100000 #
b11111111111110100000 %

#215000
b11111111111110100001 !
b11111111111111111111111110100001 #
b11111111111110100001 %

#216000
b11111111111110100010 !
b11111111111111111111111110100010 #
b11111111111110100010 %

#217000
b11111111111110100011 !
b11111111111111111111111110100011 #
b11111111111110100011 %

#218000
b11111111111110100100 !
b11111111111111111111111110100100 #
b11111111111110100100 %

#219000
b11111111111110100101 !
b11111111111111111111111110100101 #
b11111111111110100101 %

#220000
b11111111111110100110 !
b11111111111111111111111110100110 #
b11111111111110100110 %

#221000
b11111111111110100111 !
b11111111111111111111111110100111 #
b11111111111110100111 %

#222000
b11111111111110101000 !
b11111111111111111111111110101000 #
b11111111111110101000 %

#223000
b11111111111110101001 !
b11111111111111111111111110101001 #
b11111111111110101001 %

#224000
b11111111111110101010 !
b11111111111111111111111110101010 #
b11111111111110101010 %

#225000
b11111111111110101011 !
b11111111111111111111111110101011 #
b11111111111110101011 %

#226000
b11111111111110101100 !
b11111111111111111111111110101100 #
b11111111111110101100 %

#227000
b11111111111110101101 !
b11111111111111111111111110101101 #
b11111111111110101101 %

#228000
b11111111111110101110 !
b11111111111111111111111110101110 #
b11111111111110101110 %

#229000
b11111111111110101111 !
b11111111111111111111111110101111 #
b11111111111110101111 %

#230000
b11111111111110110000 !
b11111111111111111111111110110000 #
b11111111111110110000 %

#231000
b11111111111110110001 !
b11111111111111111111111110110001 #
b11111111111110110001 %

#232000
b11111111111110110010 !
b11111111111111111111111110110010 #
b11111111111110110010 %

#233000
b11111111111110110011 !
b11111111111111111111111110110011 #
b11111111111110110011 %

#234000
b11111111111110110100 !
b11111111111111111111111110110100 #
b11111111111110110100 %

#235000
b11111111111110110101 !
b11111111111111111111111110110101 #
b11111111111110110101 %

#236000
b11111111111110110110 !
b11111111111111111111111110110110 #
b11111111111110110110 %

#237000
b11111111111110110111 !
b11111111111111111111111110110111 #
b11111111111110110111 %

#238000
b11111111111110111000 !
b11111111111111111111111110111000 #
b11111111111110111000 %

#239000
b11111111111110111001 !
b11111111111111111111111110111001 #
b11111111111110111001 %

#240000
b11111111111110111010 !
b11111111111111111111111110111010 #
b11111111111110111010 %

#241000
b11111111111110111011 !
b11111111111111111111111110111011 #
b11111111111110111011 %

#242000
b11111111111110111100 !
b11111111111111111111111110111100 #
b11111111111110111100 %

#243000
b11111111111110111101 !
b11111111111111111111111110111101 #
b11111111111110111101 %

#244000
b11111111111110111110 !
b11111111111111111111111110111110 #
b11111111111110111110 %

#245000
b11111111111110111111 !
b11111111111111111111111110111111 #
b11111111111110111111 %

#246000
b11111111111111000000 !
b11111111111111111111111111000000 #
b11111111111111000000 %

#247000
b11111111111111000001 !
b11111111111111111111111111000001 #
b11111111111111000001 %

#248000
b11111111111111000010 !
b11111111111111111111111111000010 #
b11111111111111000010 %

#249000
b11111111111111000011 !
b11111111111111111111111111000011 #
b11111111111111000011 %

#250000
b11111111111111000100 !
b11111111111111111111111111000100 #
b11111111111111000100 %

#251000
b11111111111111000101 !
b11111111111111111111111111000101 #
b11111111111111000101 %

#252000
b11111111111111000110 !
b11111111111111111111111111000110 #
b11111111111111000110 %

#253000
b11111111111111000111 !
b11111111111111111111111111000111 #
b11111111111111000111 %

#254000
b11111111111111001000 !
b11111111111111111111111111001000 #
b11111111111111001000 %

#255000
b11111111111111001001 !
b11111111111111111111111111001001 #
b11111111111111001001 %

#256000
b11111111111111001010 !
b11111111111111111111111111001010 #
b11111111111111001010 %

#257000
b11111111111111001011 !
b11111111111111111111111111001011 #
b11111111111111001011 %

#258000
b11111111111111001100 !
b11111111111111111111111111001100 #
b11111111111111001100 %

#259000
b11111111111111001101 !
b11111111111111111111111111001101 #
b11111111111111001101 %

#260000
b11111111111111001110 !
b11111111111111111111111111001110 #
b11111111111111001110 %

#261000
b11111111111111001111 !
b11111111111111111111111111001111 #
b11111111111111001111 %

#262000
b11111111111111010000 !
b11111111111111111111111111010000 #
b11111111111111010000 %

#263000
b11111111111111010001 !
b11111111111111111111111111010001 #
b11111111111111010001 %

#264000
b11111111111111010010 !
b11111111111111111111111111010010 #
b11111111111111010010 %

#265000
b11111111111111010011 !
b11111111111111111111111111010011 #
b11111111111111010011 %

#266000
b11111111111111010100 !
b11111111111111111111111111010100 #
b11111111111111010100 %

#267000
b11111111111111010101 !
b11111111111111111111111111010101 #
b11111111111111010101 %

#268000
b11111111111111010110 !
b11111111111111111111111111010110 #
b11111111111111010110 %

#269000
b11111111111111010111 !
b11111111111111111111111111010111 #
b11111111111111010111 %

#270000
b11111111111111011000 !
b11111111111111111111111111011000 #
b11111111111111011000 %

#271000
b11111111111111011001 !
b11111111111111111111111111011001 #
b11111111111111011001 %

#272000
b11111111111111011010 !
b11111111111111111111111111011010 #
b11111111111111011010 %

#273000
b11111111111111011011 !
b11111111111111111111111111011011 #
b11111111111111011011 %

#274000
b11111111111111011100 !
b11111111111111111111111111011100 #
b11111111111111011100 %

#275000
b11111111111111011101 !
b11111111111111111111111111011101 #
b11111111111111011101 %

#276000
b11111111111111011110 !
b11111111111111111111111111011110 #
b11111111111111011110 %

#277000
b11111111111111011111 !
b11111111111111111111111111011111 #
b11111111111111011111 %

#278000
b11111111111111100000 !
b11111111111111111111111111100000 #
b11111111111111100000 %

#279000
b11111111111111100001 !
b11111111111111111111111111100001 #
b11111111111111100001 %

#280000
b11111111111111100010 !
b11111111111111111111111111100010 #
b11111111111111100010 %

#281000
b11111111111111100011 !
b11111111111111111111111111100011 #
b11111111111111100011 %

#282000
b11111111111111100100 !
b11111111111111111111111111100100 #
b11111111111111100100 %

#283000
b11111111111111100101 !
b11111111111111111111111111100101 #
b11111111111111100101 %

#284000
b11111111111111100110 !
b11111111111111111111111111100110 #
b11111111111111100110 %

#285000
b11111111111111100111 !
b11111111111111111111111111100111 #
b11111111111111100111 %

#286000
b11111111111111101000 !
b11111111111111111111111111101000 #
b11111111111111101000 %

#287000
b11111111111111101001 !
b11111111111111111111111111101001 #
b11111111111111101001 %

#288000
b11111111111111101010 !
b11111111111111111111111111101010 #
b11111111111111101010 %

#289000
b11111111111111101011 !
b11111111111111111111111111101011 #
b11111111111111101011 %

#290000
b11111111111111101100 !
b11111111111111111111111111101100 #
b11111111111111101100 %

#291000
b11111111111111101101 !
b11111111111111111111111111101101 #
b11111111111111101101 %

#292000
b11111111111111101110 !
b11111111111111111111111111101110 #
b11111111111111101110 %

#293000
b11111111111111101111 !
b11111111111111111111111111101111 #
b11111111111111101111 %

#294000
b11111111111111110000 !
b11111111111111111111111111110000 #
b11111111111111110000 %

#295000
b11111111111111110001 !
b11111111111111111111111111110001 #
b11111111111111110001 %

#296000
b11111111111111110010 !
b11111111111111111111111111110010 #
b11111111111111110010 %

#297000
b11111111111111110011 !
b11111111111111111111111111110011 #
b11111111111111110011 %

#298000
b11111111111111110100 !
b11111111111111111111111111110100 #
b11111111111111110100 %

#299000
b11111111111111110101 !
b11111111111111111111111111110101 #
b11111111111111110101 %

#300000
b11111111111111110110 !
b11111111111111111111111111110110 #
b11111111111111110110 %

#301000
b11111111111111110111 !
b11111111111111111111111111110111 #
b11111111111111110111 %

#302000
b11111111111111111000 !
b11111111111111111111111111111000 #
b11111111111111111000 %

#303000
b11111111111111111001 !
b11111111111111111111111111111001 #
b11111111111111111001 %

#304000
b11111111111111111010 !
b11111111111111111111111111111010 #
b11111111111111111010 %

#305000
b11111111111111111011 !
b11111111111111111111111111111011 #
b11111111111111111011 %

#306000
b11111111111111111100 !
b11111111111111111111111111111100 #
b11111111111111111100 %

#307000
b11111111111111111101 !
b11111111111111111111111111111101 #
b11111111111111111101 %

#308000
b11111111111111111110 !
b11111111111111111111111111111110 #
b11111111111111111110 %

#309000
b11111111111111111111 !
b11111111111111111111111111111111 #
b11111111111111111111 %

#310000
b0 !
b0 #
b0 %

#311000
b1 !
b1 "
b1 #
b1 $
b1 %
b1 &

#312000
b10 !
b10 "
b10 #
b10 $
b10 %
b10 &

#313000
b11 !
b11 "
b11 #
b11 $
b11 %
b11 &

#314000
b100 !
b100 "
b100 #
b100 $
b100 %
b100 &

#315000
b101 !
b101 "
b101 #
b101 $
b101 %
b101 &

#316000
b110 !
b110 "
b110 #
b110 $
b110 %
b110 &

#317000
b111 !
b111 "
b111 #
b111 $
b111 %
b111 &

#318000
b1000 !
b1000 "
b1000 #
b1000 $
b1000 %
b1000 &

#319000
b1001 !
b1001 "
b1001 #
b1001 $
b1001 %
b1001 &

#320000
b1010 !
b1010 "
b1010 #
b1010 $
b1010 %
b1010 &

#321000
b1011 !
b1011 "
b1011 #
b1011 $
b1011 %
b1011 &

#322000
b1100 !
b1100 "
b1100 #
b1100 $
b1100 %
b1100 &

#323000
b1101 !
b1101 "
b1101 #
b1101 $
b1101 %
b1101 &

#324000
b1110 !
b1110 "
b1110 #
b1110 $
b1110 %
b1110 &

#325000
b1111 !
b1111 "
b1111 #
b1111 $
b1111 %
b1111 &

#326000
b10000 !
b10000 "
b10000 #
b10000 $
b10000 %
b10000 &

#327000
b10001 !
b10001 "
b10001 #
b10001 $
b10001 %
b10001 &

#328000
b10010 !
b10010 "
b10010 #
b10010 $
b10010 %
b10010 &

#329000
b10011 !
b10011 "
b10011 #
b10011 $
b10011 %
b10011 &

#330000
b10100 !
b10100 "
b10100 #
b10100 $
b10100 %
b10100 &

#331000
b10101 !
b10101 "
b10101 #
b10101 $
b10101 %
b10101 &

#332000
b10110 !
b10110 "
b10110 #
b10110 $
b10110 %
b10110 &

#333000
b10111 !
b10111 "
b10111 #
b10111 $
b10111 %
b10111 &

#334000
b11000 !
b11000 "
b11000 #
b11000 $
b11000 %
b11000 &

#335000
b11001 !
b11001 "
b11001 #
b11001 $
b11001 %
b11001 &

#336000
b11010 !
b11010 "
b11010 #
b11010 $
b11010 %
b11010 &

#337000
b11011 !
b11011 "
b11011 #
b11011 $
b11011 %
b11011 &

#338000
b11100 !
b11100 "
b11100 #
b11100 $
b11100 %
b11100 &

#339000
b11101 !
b11101 "
b11101 #
b11101 $
b11101 %
b11101 &

#340000
b11110 !
b11110 "
b11110 #
b11110 $
b11110 %
b11110 &

#341000
b11111 !
b11111 "
b11111 #
b11111 $
b11111 %
b11111 &

#342000
b100000 !
b100000 "
b100000 #
b100000 $
b100000 %
b100000 &

#343000
b100001 !
b100001 "
b100001 #
b100001 $
b100001 %
b100001 &

#344000
b100010 !
b100010 "
b100010 #
b100010 $
b100010 %
b100010 &

#345000
b100011 !
b100011 "
b100011 #
b100011 $
b100011 %
b100011 &

#346000
b100100 !
b100100 "
b100100 #
b100100 $
b100100 %
b100100 &

